aroay_translate/__init__.py
aroay_translate/__version__.py
aroay_translate/downloadermiddlewares.py
aroay_translate/pretend.py
aroay_translate/request.py
aroay_translate/settings.py
aroay_translate-1.3.dist-info/METADATA
aroay_translate-1.3.dist-info/WHEEL
aroay_translate-1.3.dist-info/top_level.txt
aroay_translate-1.3.dist-info/RECORD
