Metadata-Version: 2.1
Name: aroay-translate
Version: 1.3
Summary: scrapy的异步翻译，最准确的翻译器
Home-page: https://github.com/hwpchn/AroayTranslate.git
Author: hwpchn
Author-email: 13692839895@163.com
License: UNKNOWN
Platform: UNKNOWN
Classifier: Programming Language :: Python :: 3
Classifier: License :: OSI Approved :: MIT License
Requires-Dist: scrapy (>=2.0.0)
Requires-Dist: pyppeteer (>=0.2.2)
